recipes_sdk/__init__.py
recipes_sdk/breakfast_1.json
recipes_sdk/breakfast_2.json
recipes_sdk/breakfast_3.json
recipes_sdk/breakfast_4.json
recipes_sdk/dinner.json
recipes_sdk/dinner_1.json
recipes_sdk/lunch.json
recipes_sdk/lunch_1.json
recipes_sdk/snack.json
recipes_sdk-0.3.0.dist-info/METADATA
recipes_sdk-0.3.0.dist-info/WHEEL
recipes_sdk-0.3.0.dist-info/top_level.txt
recipes_sdk-0.3.0.dist-info/RECORD
