Metadata-Version: 2.4
Name: recipes-sdk
Version: 0.3.0
Summary: Python SDK for working with recipes from JSON files. Includes 4819+ validated recipes across breakfast, lunch, dinner, and snack categories.
Home-page: https://github.com/krstnvt/recipes-dataset
Author: christiaansann
Author-email: 
Classifier: Programming Language :: Python :: 3
Classifier: License :: OSI Approved :: MIT License
Classifier: Operating System :: OS Independent
Requires-Python: >=3.7
Dynamic: author
Dynamic: classifier
Dynamic: description
Dynamic: description-content-type
Dynamic: home-page
Dynamic: requires-python
Dynamic: summary
